README.rst
setup.py
rl_wsd_labeled/__init__.py
rl_wsd_labeled/rl_wsd_labeled.py
rl_wsd_labeled.egg-info/PKG-INFO
rl_wsd_labeled.egg-info/SOURCES.txt
rl_wsd_labeled.egg-info/dependency_links.txt
rl_wsd_labeled.egg-info/not-zip-safe
rl_wsd_labeled.egg-info/top_level.txt
rl_wsd_labeled/adjectives/RuTenTen/авторитетный.json
rl_wsd_labeled/adjectives/RuTenTen/английский.json
rl_wsd_labeled/adjectives/RuTenTen/африканский.json
rl_wsd_labeled/adjectives/RuTenTen/белый.json
rl_wsd_labeled/adjectives/RuTenTen/беспощадный.json
rl_wsd_labeled/adjectives/RuTenTen/больной.json
rl_wsd_labeled/adjectives/RuTenTen/бронзовый.json
rl_wsd_labeled/adjectives/RuTenTen/бумажный.json
rl_wsd_labeled/adjectives/RuTenTen/вишнёвый.json
rl_wsd_labeled/adjectives/RuTenTen/воздушный.json
rl_wsd_labeled/adjectives/RuTenTen/второй.json
rl_wsd_labeled/adjectives/RuTenTen/вчерашний.json
rl_wsd_labeled/adjectives/RuTenTen/глубокий.json
rl_wsd_labeled/adjectives/RuTenTen/грубый.json
rl_wsd_labeled/nouns/RNC/альбом.txt
rl_wsd_labeled/nouns/RNC/анатомия.txt
rl_wsd_labeled/nouns/RNC/базар.txt
rl_wsd_labeled/nouns/RNC/балет.txt
rl_wsd_labeled/nouns/RNC/беда.txt
rl_wsd_labeled/nouns/RNC/бездна.txt
rl_wsd_labeled/nouns/RNC/билет.txt
rl_wsd_labeled/nouns/RNC/блок.txt
rl_wsd_labeled/nouns/RNC/блоха.txt
rl_wsd_labeled/nouns/RNC/брак.txt
rl_wsd_labeled/nouns/RNC/бритва.txt
rl_wsd_labeled/nouns/RNC/будущее.txt
rl_wsd_labeled/nouns/RNC/вешалка.txt
rl_wsd_labeled/nouns/RNC/вилка.txt
rl_wsd_labeled/nouns/RNC/винт.txt
rl_wsd_labeled/nouns/RNC/галерея.txt
rl_wsd_labeled/nouns/RNC/горбуша.txt
rl_wsd_labeled/nouns/RNC/горшок.txt
rl_wsd_labeled/nouns/RNC/гроза.txt
rl_wsd_labeled/nouns/RNC/группа.txt
rl_wsd_labeled/nouns/RuTenTen/альбом.txt
rl_wsd_labeled/nouns/RuTenTen/анатомия.txt
rl_wsd_labeled/nouns/RuTenTen/базар.txt
rl_wsd_labeled/nouns/RuTenTen/балет.txt
rl_wsd_labeled/nouns/RuTenTen/беда.txt
rl_wsd_labeled/nouns/RuTenTen/бездна.txt
rl_wsd_labeled/nouns/RuTenTen/билет.txt
rl_wsd_labeled/nouns/RuTenTen/блок.txt
rl_wsd_labeled/nouns/RuTenTen/блоха.txt
rl_wsd_labeled/nouns/RuTenTen/брак.txt
rl_wsd_labeled/nouns/RuTenTen/бритва.txt
rl_wsd_labeled/nouns/RuTenTen/будущее.txt
