Metadata-Version: 1.0
Name: rl-wsd-labeled
Version: 0.1.1
Summary: Labeled contexts of Russian polysemous words
Home-page: https://github.com/lopuhin/ruslang-wsd-labeled/
Author: Konstantin Lopuhin
Author-email: kostia.lopuhin@gmail.com
License: MIT
Platform: UNKNOWN
